streamlit_fb_post/__init__.py
streamlit_fb_post/frontend/build/asset-manifest.json
streamlit_fb_post/frontend/build/bootstrap.min.css
streamlit_fb_post/frontend/build/bootstrap.min.css.map
streamlit_fb_post/frontend/build/index.html
streamlit_fb_post/frontend/build/precache-manifest.8963ad6c8e71f12e3d880b756aa9d1ae.js
streamlit_fb_post/frontend/build/service-worker.js
streamlit_fb_post/frontend/build/static/js/2.28c7124d.chunk.js
streamlit_fb_post/frontend/build/static/js/2.28c7124d.chunk.js.LICENSE.txt
streamlit_fb_post/frontend/build/static/js/2.28c7124d.chunk.js.map
streamlit_fb_post/frontend/build/static/js/main.ce2e5b28.chunk.js
streamlit_fb_post/frontend/build/static/js/main.ce2e5b28.chunk.js.map
streamlit_fb_post/frontend/build/static/js/runtime-main.11ec9aca.js
streamlit_fb_post/frontend/build/static/js/runtime-main.11ec9aca.js.map
streamlit_fb_post-0.0.1.dist-info/LICENSE
streamlit_fb_post-0.0.1.dist-info/METADATA
streamlit_fb_post-0.0.1.dist-info/WHEEL
streamlit_fb_post-0.0.1.dist-info/top_level.txt
streamlit_fb_post-0.0.1.dist-info/RECORD
