Metadata-Version: 2.1
Name: streamlit-fb-post
Version: 0.0.1
Summary: A streamlit component, to make facebook posts
Home-page: https://github.com/gamcoh/streamlit-fb-post
Author: Gamliel Cohen <gamcoh>
Author-email: cohengamliel8@gmail.com
Keywords: chat streamlit streamlit-component facebook post ui
Classifier: Programming Language :: Python :: 3
Classifier: Operating System :: OS Independent
Requires-Python: >=3.8
License-File: LICENSE
Requires-Dist: streamlit (>=0.63)
